source_gainsight_px/__init__.py
source_gainsight_px/manifest.yaml
source_gainsight_px/run.py
source_gainsight_px/source.py
airbyte_source_gainsight_px-0.1.14.dist-info/METADATA
airbyte_source_gainsight_px-0.1.14.dist-info/WHEEL
airbyte_source_gainsight_px-0.1.14.dist-info/entry_points.txt
airbyte_source_gainsight_px-0.1.14.dist-info/RECORD
