Metadata-Version: 2.1
Name: airbyte-source-gainsight-px
Version: 0.1.14
Summary: Source implementation for Gainsight Px.
Home-page: https://airbyte.com
License: MIT
Author: Airbyte
Author-email: contact@airbyte.io
Requires-Python: >=3.9,<3.12
Classifier: License :: OSI Approved :: MIT License
Classifier: Programming Language :: Python :: 3
Classifier: Programming Language :: Python :: 3.9
Classifier: Programming Language :: Python :: 3.10
Classifier: Programming Language :: Python :: 3.11
Requires-Dist: airbyte-cdk (>=0,<1)
Project-URL: Documentation, https://docs.airbyte.com/integrations/sources/gainsight-px
Project-URL: Repository, https://github.com/airbytehq/airbyte
